pytest_otel/__init__.py
pytest_otel-2.0.2.dist-info/licenses/LICENSE
pytest_otel-2.0.2.dist-info/METADATA
pytest_otel-2.0.2.dist-info/WHEEL
pytest_otel-2.0.2.dist-info/entry_points.txt
pytest_otel-2.0.2.dist-info/top_level.txt
pytest_otel-2.0.2.dist-info/RECORD
