Metadata-Version: 2.4
Name: pytest_otel
Version: 2.0.2
Summary: OpenTelemetry plugin for Pytest
Author: Ivan Fernandez Calvo (kuisathaverat)
License:                                  Apache License
Keywords: pytest,otel,opentelemetry,debug
Classifier: Environment :: Plugins
Classifier: Framework :: Pytest
Classifier: Intended Audience :: Developers
Classifier: License :: OSI Approved :: Apache Software License
Classifier: Operating System :: OS Independent
Classifier: Programming Language :: Python :: 3
Classifier: Programming Language :: Python :: 3.10
Classifier: Programming Language :: Python :: 3.11
Classifier: Programming Language :: Python :: 3.12
Classifier: Programming Language :: Python :: 3.13
Classifier: Programming Language :: Python :: 3.14
Classifier: Topic :: Software Development :: Libraries
Classifier: Topic :: Software Development :: Testing
Classifier: Topic :: Utilities
Requires-Python: >=3.10
License-File: LICENSE
Requires-Dist: opentelemetry-api==1.39.1
Requires-Dist: opentelemetry-exporter-otlp==1.39.1
Requires-Dist: opentelemetry-sdk==1.39.1
Requires-Dist: pytest==9.0.2
Provides-Extra: test
Requires-Dist: pytest-cov==7.0.0; extra == "test"
Requires-Dist: pre-commit==4.5.0; extra == "test"
Requires-Dist: pytest-docker==3.2.5; extra == "test"
Requires-Dist: mypy==1.19.0; extra == "test"
Requires-Dist: black==25.12.0; extra == "test"
Requires-Dist: flake8==7.3.0; extra == "test"
Requires-Dist: build==1.3.0; extra == "test"
Requires-Dist: twine==6.2.0; extra == "test"
Dynamic: license-file
